ssh_gpu_monitor/__init__.py
ssh_gpu_monitor/__main__.py
ssh_gpu_monitor/main.py
ssh_gpu_monitor/config/config.yaml
ssh_gpu_monitor/src/__init__.py
ssh_gpu_monitor/src/config_loader.py
ssh_gpu_monitor/src/table_display.py
ssh_gpu_monitor-1.0.2.dist-info/LICENSE
ssh_gpu_monitor-1.0.2.dist-info/METADATA
ssh_gpu_monitor-1.0.2.dist-info/WHEEL
ssh_gpu_monitor-1.0.2.dist-info/entry_points.txt
ssh_gpu_monitor-1.0.2.dist-info/top_level.txt
ssh_gpu_monitor-1.0.2.dist-info/RECORD
