Metadata-Version: 2.1
Name: ssh-gpu-monitor
Version: 1.0.2
Summary: A fast, asynchronous GPU monitoring tool for multiple machines through SSH
Author-email: Alex Spies <alex@afspies.com>
License: MIT License
Project-URL: Homepage, https://github.com/afspies/gpu-monitor
Project-URL: Bug Tracker, https://github.com/afspies/gpu-monitor/issues
Classifier: Programming Language :: Python :: 3
Classifier: Programming Language :: Python :: 3.9
Classifier: Programming Language :: Python :: 3.10
Classifier: Programming Language :: Python :: 3.11
Classifier: License :: OSI Approved :: MIT License
Classifier: Operating System :: OS Independent
Classifier: Development Status :: 4 - Beta
Classifier: Environment :: Console
Classifier: Topic :: System :: Monitoring
Classifier: Topic :: System :: Systems Administration
Requires-Python: >=3.9
License-File: LICENSE
Requires-Dist: rich>=10.0.0
Requires-Dist: asyncssh>=2.13.1
Requires-Dist: pyyaml>=6.0.1
Requires-Dist: pyOpenSSL==23.1.1
Requires-Dist: cryptography==40.0.2
